xes/AIspeak.py
xes/__init__.py
xes/aiBase.py
xes/common.py
xes/data.py
xes/ext.py
xes/garbage.py
xes/library.py
xes/map.py
xes/provinces.py
xes/sms.py
xes/timesecret.py
xes/tool.py
xes/uploader.py
xes/version.py
xes/weather.py
xes/word.py
xes_lib-0.1.36.dist-info/METADATA
xes_lib-0.1.36.dist-info/WHEEL
xes_lib-0.1.36.dist-info/top_level.txt
xes_lib-0.1.36.dist-info/RECORD
